EphysAnalysis/APP.py
EphysAnalysis/__init__.py
EphysAnalysis/error.py
EphysAnalysis/event_signal.py
EphysAnalysis/feature_extractor.py
EphysAnalysis/features.py
EphysAnalysis/qc_features.py
EphysAnalysis/signal_filters.py
EphysAnalysis/spike_detector.py
EphysAnalysis/spike_features.py
EphysAnalysis/spike_train_features.py
EphysAnalysis/subthresh_features.py
EphysAnalysis/time_series_utils.py
ephys_analysis-0.1.6.dist-info/licenses/LICENSE
ephys_analysis-0.1.6.dist-info/METADATA
ephys_analysis-0.1.6.dist-info/WHEEL
ephys_analysis-0.1.6.dist-info/entry_points.txt
ephys_analysis-0.1.6.dist-info/top_level.txt
ephys_analysis-0.1.6.dist-info/RECORD
