Metadata-Version: 2.4
Name: ephys-analysis
Version: 0.1.6
Summary: Electrophysiology data analysis
Author: Unknown
License: Allen Institute Software License - This software license is the 2-clause BSD license plus a third clause that prohibits redistribution for commercial purposes without further permission.
Requires-Python: >=3.8
License-File: LICENSE
Requires-Dist: numpy
Requires-Dist: pandas
Requires-Dist: pyabf
Requires-Dist: tk
Requires-Dist: peakutils
Requires-Dist: scipy
Requires-Dist: tqdm
Dynamic: license-file
